{
    "order_id": 550169,
    "client_id": 2127,
    "produits": [
        {
            "produit_id": "P6380",
            "nom": "Small Cheese",
            "quantite": 4,
            "prix_unitaire": 33.09
        },
        {
            "produit_id": "P7206",
            "nom": "Small Fresh Hat",
            "quantite": 5,
            "prix_unitaire": 452.32
        },
        {
            "produit_id": "P1286",
            "nom": "Licensed Steel Computer",
            "quantite": 2,
            "prix_unitaire": 358.17
        }
    ],
    "date_commande": "2024-11-26T19:42:15",
    "canal": "boutique",
    "statut_commande": "payée"
}